geokitten/__init__.py
geokitten/gdf_kml_converter.py
geokitten/gdf_standardization.py
geokitten/html_generator.py
geokitten-0.1.3.dist-info/licenses/LICENSE
geokitten-0.1.3.dist-info/METADATA
geokitten-0.1.3.dist-info/WHEEL
geokitten-0.1.3.dist-info/top_level.txt
geokitten-0.1.3.dist-info/RECORD
