Metadata-Version: 2.4
Name: geokitten
Version: 0.1.3
Summary: Tools for geospatial data processing and visualization
Home-page: https://github.com/sape94/GeoKitten
Author: sape94
Author-email: sergioapelayoe@gmail.com
Classifier: Programming Language :: Python :: 3
Classifier: License :: OSI Approved :: MIT License
Classifier: Operating System :: OS Independent
Classifier: Topic :: Scientific/Engineering :: GIS
Requires-Python: >=3.9
License-File: LICENSE
Requires-Dist: geopandas>=0.9.0
Requires-Dist: numpy>=1.23.4
Requires-Dist: geopandas>=0.14.2
Requires-Dist: pandas>=2.2.2
Requires-Dist: shapely>=2.0.2
Requires-Dist: pytest>=8.3.5
Requires-Dist: fiona>=1.8.22
Requires-Dist: folium>=0.14.0
Requires-Dist: branca>=0.6.0
Requires-Dist: matplotlib>=3.7.1
Provides-Extra: dev
Requires-Dist: pytest>=8.3; extra == "dev"
Dynamic: author
Dynamic: author-email
Dynamic: classifier
Dynamic: description
Dynamic: description-content-type
Dynamic: home-page
Dynamic: license-file
Dynamic: provides-extra
Dynamic: requires-dist
Dynamic: requires-python
Dynamic: summary
